novaeval/__init__.py
novaeval/cli.py
novaeval/py.typed
novaeval/agents/__init__.py
novaeval/agents/agent_data.py
novaeval/config/__init__.py
novaeval/config/job_config.py
novaeval/config/schema.py
novaeval/datasets/__init__.py
novaeval/datasets/agent_dataset.py
novaeval/datasets/base.py
novaeval/datasets/custom.py
novaeval/datasets/huggingface.py
novaeval/datasets/mmlu.py
novaeval/datasets/noveum_spans_dataset.py
novaeval/datasets/swe_agent_trajectories_dataset.py
novaeval/evaluators/__init__.py
novaeval/evaluators/agent_evaluator.py
novaeval/evaluators/aggregators.py
novaeval/evaluators/base.py
novaeval/evaluators/standard.py
novaeval/integrations/__init__.py
novaeval/integrations/noveum.py
novaeval/models/__init__.py
novaeval/models/anthropic.py
novaeval/models/azure_openai.py
novaeval/models/base.py
novaeval/models/gemini.py
novaeval/models/ollama.py
novaeval/models/openai.py
novaeval/noveum_platform/__init__.py
novaeval/noveum_platform/client.py
novaeval/noveum_platform/exceptions.py
novaeval/noveum_platform/models.py
novaeval/noveum_platform/noveum_datasets_api.py
novaeval/noveum_platform/noveum_scorer_results_api.py
novaeval/noveum_platform/noveum_traces_api.py
novaeval/noveum_platform/utils.py
novaeval/reporting/__init__.py
novaeval/reporting/metrics.py
novaeval/scorers/__init__.py
novaeval/scorers/accuracy.py
novaeval/scorers/advanced_generation_scorers.py
novaeval/scorers/agent_scorers.py
novaeval/scorers/agent_scorers_system_prompts.py
novaeval/scorers/base.py
novaeval/scorers/basic_rag_scorers.py
novaeval/scorers/conversational.py
novaeval/scorers/g_eval.py
novaeval/scorers/panel_judge.py
novaeval/scorers/rag.py
novaeval/scorers/rag_pipeline_evaluator.py
novaeval/scorers/rag_prompts.py
novaeval/utils/__init__.py
novaeval/utils/config.py
novaeval/utils/json_parser.py
novaeval/utils/llm.py
novaeval/utils/logging.py
novaeval/utils/parsing.py
novaeval-0.7.0.dist-info/licenses/LICENSE
novaeval-0.7.0.dist-info/METADATA
novaeval-0.7.0.dist-info/WHEEL
novaeval-0.7.0.dist-info/entry_points.txt
novaeval-0.7.0.dist-info/top_level.txt
novaeval-0.7.0.dist-info/RECORD
