Metadata-Version: 2.4
Name: novaeval
Version: 0.7.0
Summary: A comprehensive, open-source LLM evaluation framework for testing and benchmarking AI models
Author-email: Noveum AI <team@noveum.ai>
Maintainer-email: Noveum AI <team@noveum.ai>
License:                                  Apache License
Project-URL: Homepage, https://github.com/Noveum/NovaEval
Project-URL: Documentation, https://novaeval.readthedocs.io
Project-URL: Repository, https://github.com/Noveum/NovaEval
Project-URL: Bug Tracker, https://github.com/Noveum/NovaEval/issues
Project-URL: Changelog, https://github.com/Noveum/NovaEval/blob/main/CHANGELOG.md
Keywords: llm,evaluation,ai,machine-learning,benchmarking,testing,rag,agents,conversational-ai,g-eval
Classifier: Development Status :: 3 - Alpha
Classifier: Intended Audience :: Developers
Classifier: Intended Audience :: Science/Research
Classifier: Operating System :: OS Independent
Classifier: Programming Language :: Python :: 3
Classifier: Programming Language :: Python :: 3.9
Classifier: Programming Language :: Python :: 3.10
Classifier: Programming Language :: Python :: 3.11
Classifier: Programming Language :: Python :: 3.12
Classifier: Topic :: Scientific/Engineering :: Artificial Intelligence
Classifier: Topic :: Software Development :: Testing
Classifier: Topic :: Software Development :: Quality Assurance
Requires-Python: >=3.9
License-File: LICENSE
Requires-Dist: pydantic>=2.5.0
Requires-Dist: httpx>=0.25.0
Requires-Dist: tenacity>=8.2.0
Requires-Dist: rich>=13.0.0
Requires-Dist: typer>=0.9.0
Requires-Dist: pyyaml>=6.0
Requires-Dist: jinja2>=3.1.0
Requires-Dist: numpy>=1.24.0
Requires-Dist: pandas>=2.0.0
Requires-Dist: datasets>=2.14.0
Requires-Dist: openai>=1.3.0
Requires-Dist: anthropic>=0.8.0
Requires-Dist: tiktoken>=0.5.0
Requires-Dist: sentence-transformers>=2.2.0
Requires-Dist: tqdm>=4.66.0
Requires-Dist: click>=8.1.0
Requires-Dist: requests>=2.31.0
Requires-Dist: google-genai>=0.1.0
Requires-Dist: ijson>=3.4.0
Requires-Dist: noveum-trace>=0.3.5
Requires-Dist: python-dotenv>=1.0.0
Requires-Dist: ollama>=0.5.3
Requires-Dist: transformers>=4.20.0
Requires-Dist: scikit-learn>=1.0.0
Requires-Dist: plotly>=5.0.0
Provides-Extra: dev
Requires-Dist: pytest>=7.4.0; extra == "dev"
Requires-Dist: pytest-cov>=4.1.0; extra == "dev"
Requires-Dist: pytest-asyncio>=0.21.0; extra == "dev"
Requires-Dist: pytest-mock>=3.11.0; extra == "dev"
Requires-Dist: pytest-xdist>=3.3.0; extra == "dev"
Requires-Dist: responses>=0.23.0; extra == "dev"
Requires-Dist: black>=23.9.0; extra == "dev"
Requires-Dist: isort>=5.12.0; extra == "dev"
Requires-Dist: ruff>=0.1.0; extra == "dev"
Requires-Dist: mypy>=1.6.0; extra == "dev"
Requires-Dist: typing_extensions>=4.7.0; extra == "dev"
Requires-Dist: pre-commit>=3.5.0; extra == "dev"
Requires-Dist: bandit>=1.7.5; extra == "dev"
Requires-Dist: safety>=2.3.0; extra == "dev"
Requires-Dist: coverage>=7.3.0; extra == "dev"
Requires-Dist: sphinx>=7.2.0; extra == "dev"
Requires-Dist: sphinx-rtd-theme>=1.3.0; extra == "dev"
Requires-Dist: myst-parser>=2.0.0; extra == "dev"
Requires-Dist: jupyter>=1.0.0; extra == "dev"
Requires-Dist: ipykernel>=6.25.0; extra == "dev"
Requires-Dist: commitizen>=3.12.0; extra == "dev"
Provides-Extra: docs
Requires-Dist: sphinx>=7.2.0; extra == "docs"
Requires-Dist: sphinx-rtd-theme>=1.3.0; extra == "docs"
Requires-Dist: myst-parser>=2.0.0; extra == "docs"
Requires-Dist: sphinx-autodoc-typehints>=1.24.0; extra == "docs"
Requires-Dist: sphinx-copybutton>=0.5.2; extra == "docs"
Provides-Extra: azure
Requires-Dist: azure-ai-inference>=1.0.0; python_version < "3.11" and extra == "azure"
Provides-Extra: aws
Requires-Dist: boto3>=1.34.0; extra == "aws"
Provides-Extra: gcp
Requires-Dist: google-cloud-aiplatform>=1.38.0; extra == "gcp"
Provides-Extra: api
Requires-Dist: fastapi>=0.110.0; extra == "api"
Requires-Dist: uvicorn[standard]>=0.25.0; extra == "api"
Requires-Dist: python-dotenv>=1.0.0; extra == "api"
Requires-Dist: python-multipart>=0.0.6; extra == "api"
Requires-Dist: pydantic-settings>=2.0.0; extra == "api"
Requires-Dist: prometheus_client>=0.17.0; extra == "api"
Provides-Extra: all
Requires-Dist: pytest>=7.4.0; extra == "all"
Requires-Dist: pytest-cov>=4.1.0; extra == "all"
Requires-Dist: pytest-asyncio>=0.21.0; extra == "all"
Requires-Dist: pytest-mock>=3.11.0; extra == "all"
Requires-Dist: pytest-xdist>=3.3.0; extra == "all"
Requires-Dist: responses>=0.23.0; extra == "all"
Requires-Dist: black>=23.9.0; extra == "all"
Requires-Dist: isort>=5.12.0; extra == "all"
Requires-Dist: ruff>=0.1.0; extra == "all"
Requires-Dist: mypy>=1.6.0; extra == "all"
Requires-Dist: typing_extensions>=4.7.0; extra == "all"
Requires-Dist: pre-commit>=3.5.0; extra == "all"
Requires-Dist: bandit>=1.7.5; extra == "all"
Requires-Dist: safety>=2.3.0; extra == "all"
Requires-Dist: coverage>=7.3.0; extra == "all"
Requires-Dist: sphinx>=7.2.0; extra == "all"
Requires-Dist: sphinx-rtd-theme>=1.3.0; extra == "all"
Requires-Dist: myst-parser>=2.0.0; extra == "all"
Requires-Dist: jupyter>=1.0.0; extra == "all"
Requires-Dist: ipykernel>=6.25.0; extra == "all"
Requires-Dist: commitizen>=3.12.0; extra == "all"
Requires-Dist: sphinx-autodoc-typehints>=1.24.0; extra == "all"
Requires-Dist: sphinx-copybutton>=0.5.2; extra == "all"
Requires-Dist: azure-ai-inference>=1.0.0; python_version < "3.11" and extra == "all"
Requires-Dist: boto3>=1.34.0; extra == "all"
Requires-Dist: google-cloud-aiplatform>=1.38.0; extra == "all"
Dynamic: license-file
